LICENSE
MANIFEST.in
README.md
setup.py
gears_sass/__init__.py
gears_sass/compiler.js
gears_sass/compiler.py
gears_sass.egg-info/PKG-INFO
gears_sass.egg-info/SOURCES.txt
gears_sass.egg-info/dependency_links.txt
gears_sass.egg-info/top_level.txt
gears_sass/node_modules/.bin/node-sass
gears_sass/node_modules/node-sass/.editorconfig
gears_sass/node_modules/node-sass/.gitmodules
gears_sass/node_modules/node-sass/.jshintignore
gears_sass/node_modules/node-sass/.jshintrc
gears_sass/node_modules/node-sass/.npmignore
gears_sass/node_modules/node-sass/.travis.yml
gears_sass/node_modules/node-sass/CONTRIBUTING.md
gears_sass/node_modules/node-sass/LICENSE
gears_sass/node_modules/node-sass/README.md
gears_sass/node_modules/node-sass/binding.cpp
gears_sass/node_modules/node-sass/binding.gyp
gears_sass/node_modules/node-sass/build.js
gears_sass/node_modules/node-sass/package.json
gears_sass/node_modules/node-sass/sass.js
gears_sass/node_modules/node-sass/sass_context_wrapper.cpp
gears_sass/node_modules/node-sass/sass_context_wrapper.h
gears_sass/node_modules/node-sass/bin/node-sass
gears_sass/node_modules/node-sass/bin/darwin-x64-v8-3.14/binding.node
gears_sass/node_modules/node-sass/bin/linux-ia32-v8-3.14/binding.node
gears_sass/node_modules/node-sass/bin/linux-x64-v8-3.14/binding.node
gears_sass/node_modules/node-sass/bin/win32-ia32-v8-3.14/binding.node
gears_sass/node_modules/node-sass/bin/win32-x64-v8-3.14/binding.node
gears_sass/node_modules/node-sass/examples/middleware.js
gears_sass/node_modules/node-sass/examples/test.scss
gears_sass/node_modules/node-sass/examples/public/.npmignore
gears_sass/node_modules/node-sass/lib/cli.js
gears_sass/node_modules/node-sass/lib/middleware.js
gears_sass/node_modules/node-sass/lib/render.js
gears_sass/node_modules/node-sass/libsass/.editorconfig
gears_sass/node_modules/node-sass/libsass/.gitattributes
gears_sass/node_modules/node-sass/libsass/.npmignore
gears_sass/node_modules/node-sass/libsass/.travis.yml
gears_sass/node_modules/node-sass/libsass/COPYING
gears_sass/node_modules/node-sass/libsass/INSTALL
gears_sass/node_modules/node-sass/libsass/LICENSE
