Metadata-Version: 1.1
Name: gears-sass
Version: 0.2.1
Summary: SASS compiler for Gears
Home-page: https://github.com/ChillyBwoy/gears-sass
Author: Eugene Cheltsov
Author-email: chill.icp@gmail.com
License: ISC
Keywords: gears django-gears gears-sass gears-scss
Platform: UNKNOWN
Classifier: Development Status :: 3 - Alpha
Classifier: Intended Audience :: Developers
Classifier: License :: OSI Approved :: ISC License (ISCL)
Classifier: Operating System :: OS Independent
Classifier: Programming Language :: Python
Classifier: Programming Language :: Python :: 2.7
